cronexpressions/__init__.py
cronexpressions/builder.py
cronexpressions/expressions.py
cronexpressions-0.1.1.dist-info/METADATA
cronexpressions-0.1.1.dist-info/WHEEL
cronexpressions-0.1.1.dist-info/top_level.txt
cronexpressions-0.1.1.dist-info/RECORD
