Metadata-Version: 2.1
Name: cronexpressions
Version: 0.1.1
Summary: A library for predefined and custom cron expressions
Home-page: https://github.com/poysa213/cronexpressions.git
Author: Youcef Hanaia
Author-email: hanaiayoucef@gmail.com
License: MIT
Classifier: Programming Language :: Python :: 3
Classifier: License :: OSI Approved :: MIT License
Classifier: Operating System :: OS Independent
Requires-Python: >=3.6
